{"NAME_CONTRACT_TYPE":0.0,"CODE_GENDER":1.0,"FLAG_OWN_CAR":1.0,"FLAG_OWN_REALTY":1.0,"CNT_CHILDREN":0.0,"AMT_INCOME_TOTAL":166500.0,"AMT_CREDIT":155938.5,"AMT_ANNUITY":14431.5,"AMT_GOODS_PRICE":126000.0,"NAME_TYPE_SUITE":7.0,"NAME_INCOME_TYPE":1.0,"NAME_EDUCATION_TYPE":4.0,"NAME_FAMILY_STATUS":1.0,"NAME_HOUSING_TYPE":1.0,"REGION_POPULATION_RELATIVE":0.025164,"DAYS_BIRTH":-15466.0,"DAYS_EMPLOYED":-3847.0,"DAYS_REGISTRATION":-2363.0,"DAYS_ID_PUBLISH":-4350.0,"OWN_CAR_AGE":8.0,"FLAG_MOBIL":1.0,"FLAG_EMP_PHONE":1.0,"FLAG_WORK_PHONE":0.0,"FLAG_CONT_MOBILE":1.0,"FLAG_PHONE":1.0,"FLAG_EMAIL":0.0,"OCCUPATION_TYPE":8.0,"CNT_FAM_MEMBERS":2.0,"REGION_RATING_CLIENT":2.0,"REGION_RATING_CLIENT_W_CITY":2.0,"WEEKDAY_APPR_PROCESS_START":0.0,"HOUR_APPR_PROCESS_START":14.0,"REG_REGION_NOT_LIVE_REGION":0.0,"REG_REGION_NOT_WORK_REGION":0.0,"LIVE_REGION_NOT_WORK_REGION":0.0,"REG_CITY_NOT_LIVE_CITY":0.0,"REG_CITY_NOT_WORK_CITY":0.0,"LIVE_CITY_NOT_WORK_CITY":0.0,"ORGANIZATION_TYPE":5.0,"EXT_SOURCE_1":null,"EXT_SOURCE_2":0.2457222384,"EXT_SOURCE_3":0.5726825047,"APARTMENTS_AVG":0.2969,"BASEMENTAREA_AVG":0.1459,"YEARS_BEGINEXPLUATATION_AVG":0.9916,"YEARS_BUILD_AVG":0.8844,"COMMONAREA_AVG":0.0402,"ELEVATORS_AVG":0.32,"ENTRANCES_AVG":0.2759,"FLOORSMAX_AVG":0.375,"FLOORSMIN_AVG":0.4167,"LANDAREA_AVG":0.0205,"LIVINGAPARTMENTS_AVG":0.2421,"LIVINGAREA_AVG":0.2944,"NONLIVINGAPARTMENTS_AVG":0.0,"NONLIVINGAREA_AVG":0.0,"APARTMENTS_MODE":0.3025,"BASEMENTAREA_MODE":0.1514,"YEARS_BEGINEXPLUATATION_MODE":0.9916,"YEARS_BUILD_MODE":0.8889,"COMMONAREA_MODE":0.0406,"ELEVATORS_MODE":0.3222,"ENTRANCES_MODE":0.2759,"FLOORSMAX_MODE":0.375,"FLOORSMIN_MODE":0.4167,"LANDAREA_MODE":0.021,"LIVINGAPARTMENTS_MODE":0.2645,"LIVINGAREA_MODE":0.3067,"NONLIVINGAPARTMENTS_MODE":0.0,"NONLIVINGAREA_MODE":0.0,"APARTMENTS_MEDI":0.2998,"BASEMENTAREA_MEDI":0.1459,"YEARS_BEGINEXPLUATATION_MEDI":0.9916,"YEARS_BUILD_MEDI":0.8859,"COMMONAREA_MEDI":0.0404,"ELEVATORS_MEDI":0.32,"ENTRANCES_MEDI":0.2759,"FLOORSMAX_MEDI":0.375,"FLOORSMIN_MEDI":0.4167,"LANDAREA_MEDI":0.0209,"LIVINGAPARTMENTS_MEDI":0.2463,"LIVINGAREA_MEDI":0.2997,"NONLIVINGAPARTMENTS_MEDI":0.0,"NONLIVINGAREA_MEDI":0.0,"FONDKAPREMONT_MODE":4.0,"HOUSETYPE_MODE":1.0,"TOTALAREA_MODE":0.2315,"WALLSMATERIAL_MODE":5.0,"EMERGENCYSTATE_MODE":1.0,"OBS_30_CNT_SOCIAL_CIRCLE":2.0,"DEF_30_CNT_SOCIAL_CIRCLE":1.0,"OBS_60_CNT_SOCIAL_CIRCLE":2.0,"DEF_60_CNT_SOCIAL_CIRCLE":1.0,"DAYS_LAST_PHONE_CHANGE":-1923.0,"FLAG_DOCUMENT_2":0.0,"FLAG_DOCUMENT_3":1.0,"FLAG_DOCUMENT_4":0.0,"FLAG_DOCUMENT_5":0.0,"FLAG_DOCUMENT_6":0.0,"FLAG_DOCUMENT_7":0.0,"FLAG_DOCUMENT_8":0.0,"FLAG_DOCUMENT_9":0.0,"FLAG_DOCUMENT_10":0.0,"FLAG_DOCUMENT_11":0.0,"FLAG_DOCUMENT_12":0.0,"FLAG_DOCUMENT_13":0.0,"FLAG_DOCUMENT_14":0.0,"FLAG_DOCUMENT_15":0.0,"FLAG_DOCUMENT_16":0.0,"FLAG_DOCUMENT_17":0.0,"FLAG_DOCUMENT_18":0.0,"FLAG_DOCUMENT_19":0.0,"FLAG_DOCUMENT_20":0.0,"FLAG_DOCUMENT_21":0.0,"AMT_REQ_CREDIT_BUREAU_HOUR":0.0,"AMT_REQ_CREDIT_BUREAU_DAY":0.0,"AMT_REQ_CREDIT_BUREAU_WEEK":0.0,"AMT_REQ_CREDIT_BUREAU_MON":0.0,"AMT_REQ_CREDIT_BUREAU_QRT":1.0,"AMT_REQ_CREDIT_BUREAU_YEAR":3.0,"DAYS_EMPLOYED_PERC":0.2487391698,"INCOME_CREDIT_PERC":1.0677286238,"INCOME_PER_PERSON":83250.0,"ANNUITY_INCOME_PERC":0.0866756757,"PAYMENT_RATE":0.0925460999,"BURO_DAYS_CREDIT_MIN":-2782.0,"BURO_DAYS_CREDIT_MAX":-513.0,"BURO_DAYS_CREDIT_MEAN":-1386.2666666667,"BURO_DAYS_CREDIT_VAR":659190.3523809524,"BURO_DAYS_CREDIT_ENDDATE_MIN":-2464.0,"BURO_DAYS_CREDIT_ENDDATE_MAX":1326.0,"BURO_DAYS_CREDIT_ENDDATE_MEAN":-518.5,"BURO_DAYS_CREDIT_UPDATE_MEAN":-855.8,"BURO_CREDIT_DAY_OVERDUE_MAX":0.0,"BURO_CREDIT_DAY_OVERDUE_MEAN":0.0,"BURO_AMT_CREDIT_MAX_OVERDUE_MEAN":0.0,"BURO_AMT_CREDIT_SUM_MAX":1451767.5,"BURO_AMT_CREDIT_SUM_MEAN":278144.694,"BURO_AMT_CREDIT_SUM_SUM":4172170.4100000001,"BURO_AMT_CREDIT_SUM_DEBT_MAX":433660.5,"BURO_AMT_CREDIT_SUM_DEBT_MEAN":33358.5,"BURO_AMT_CREDIT_SUM_DEBT_SUM":433660.5,"BURO_AMT_CREDIT_SUM_OVERDUE_MEAN":0.0,"BURO_AMT_CREDIT_SUM_LIMIT_MEAN":20500.0,"BURO_AMT_CREDIT_SUM_LIMIT_SUM":184500.0,"BURO_AMT_ANNUITY_MAX":24093.0,"BURO_AMT_ANNUITY_MEAN":8451.0,"BURO_CNT_CREDIT_PROLONG_SUM":0.0,"BURO_MONTHS_BALANCE_MIN_MIN":-91.0,"BURO_MONTHS_BALANCE_MAX_MAX":0.0,"BURO_MONTHS_BALANCE_SIZE_MEAN":45.4666666667,"BURO_MONTHS_BALANCE_SIZE_SUM":682.0,"ACTIVE_DAYS_CREDIT_MIN":-1156.0,"ACTIVE_DAYS_CREDIT_MAX":-513.0,"ACTIVE_DAYS_CREDIT_MEAN":-658.0,"ACTIVE_DAYS_CREDIT_VAR":78499.5,"ACTIVE_DAYS_CREDIT_ENDDATE_MIN":508.0,"ACTIVE_DAYS_CREDIT_ENDDATE_MAX":1326.0,"ACTIVE_DAYS_CREDIT_ENDDATE_MEAN":1075.5,"ACTIVE_DAYS_CREDIT_UPDATE_MEAN":-252.6,"ACTIVE_CREDIT_DAY_OVERDUE_MAX":0.0,"ACTIVE_CREDIT_DAY_OVERDUE_MEAN":0.0,"ACTIVE_AMT_CREDIT_MAX_OVERDUE_MEAN":null,"ACTIVE_AMT_CREDIT_SUM_MAX":626584.5,"ACTIVE_AMT_CREDIT_SUM_MEAN":208116.9,"ACTIVE_AMT_CREDIT_SUM_SUM":1040584.5,"ACTIVE_AMT_CREDIT_SUM_DEBT_MAX":433660.5,"ACTIVE_AMT_CREDIT_SUM_DEBT_MEAN":86732.1,"ACTIVE_AMT_CREDIT_SUM_DEBT_SUM":433660.5,"ACTIVE_AMT_CREDIT_SUM_OVERDUE_MEAN":0.0,"ACTIVE_AMT_CREDIT_SUM_LIMIT_MEAN":46125.0,"ACTIVE_AMT_CREDIT_SUM_LIMIT_SUM":184500.0,"ACTIVE_AMT_ANNUITY_MAX":24093.0,"ACTIVE_AMT_ANNUITY_MEAN":12046.5,"ACTIVE_CNT_CREDIT_PROLONG_SUM":0.0,"ACTIVE_MONTHS_BALANCE_MIN_MIN":-38.0,"ACTIVE_MONTHS_BALANCE_MAX_MAX":0.0,"ACTIVE_MONTHS_BALANCE_SIZE_MEAN":21.6,"ACTIVE_MONTHS_BALANCE_SIZE_SUM":108.0,"CLOSED_DAYS_CREDIT_MIN":-2782.0,"CLOSED_DAYS_CREDIT_MAX":-930.0,"CLOSED_DAYS_CREDIT_MEAN":-1750.4,"CLOSED_DAYS_CREDIT_VAR":548541.6000000001,"CLOSED_DAYS_CREDIT_ENDDATE_MIN":-2464.0,"CLOSED_DAYS_CREDIT_ENDDATE_MAX":-511.0,"CLOSED_DAYS_CREDIT_ENDDATE_MEAN":-1156.1,"CLOSED_DAYS_CREDIT_UPDATE_MEAN":-1157.4,"CLOSED_CREDIT_DAY_OVERDUE_MAX":0.0,"CLOSED_CREDIT_DAY_OVERDUE_MEAN":0.0,"CLOSED_AMT_CREDIT_MAX_OVERDUE_MEAN":0.0,"CLOSED_AMT_CREDIT_SUM_MAX":1451767.5,"CLOSED_AMT_CREDIT_SUM_MEAN":313158.591,"CLOSED_AMT_CREDIT_SUM_SUM":3131585.9100000001,"CLOSED_AMT_CREDIT_SUM_DEBT_MAX":0.0,"CLOSED_AMT_CREDIT_SUM_DEBT_MEAN":0.0,"CLOSED_AMT_CREDIT_SUM_DEBT_SUM":0.0,"CLOSED_AMT_CREDIT_SUM_OVERDUE_MEAN":0.0,"CLOSED_AMT_CREDIT_SUM_LIMIT_MEAN":0.0,"CLOSED_AMT_CREDIT_SUM_LIMIT_SUM":0.0,"CLOSED_AMT_ANNUITY_MAX":23800.5,"CLOSED_AMT_ANNUITY_MEAN":7012.8,"CLOSED_CNT_CREDIT_PROLONG_SUM":0.0,"CLOSED_MONTHS_BALANCE_MIN_MIN":-91.0,"CLOSED_MONTHS_BALANCE_MAX_MAX":0.0,"CLOSED_MONTHS_BALANCE_SIZE_MEAN":57.4,"CLOSED_MONTHS_BALANCE_SIZE_SUM":574.0,"PREV_AMT_ANNUITY_MIN":4774.005,"PREV_AMT_ANNUITY_MAX":34253.1,"PREV_AMT_ANNUITY_MEAN":16270.5395454545,"PREV_AMT_APPLICATION_MIN":0.0,"PREV_AMT_APPLICATION_MAX":1129500.0,"PREV_AMT_APPLICATION_MEAN":197266.5,"PREV_AMT_CREDIT_MIN":0.0,"PREV_AMT_CREDIT_MAX":1293502.5,"PREV_AMT_CREDIT_MEAN":222060.8571428571,"PREV_APP_CREDIT_PERC_MIN":0.7594185702,"PREV_APP_CREDIT_PERC_MAX":1.1836734694,"PREV_APP_CREDIT_PERC_MEAN":0.9722822789,"PREV_APP_CREDIT_PERC_VAR":0.0191935889,"PREV_AMT_DOWN_PAYMENT_MIN":4698.0,"PREV_AMT_DOWN_PAYMENT_MAX":15876.0,"PREV_AMT_DOWN_PAYMENT_MEAN":8361.0,"PREV_AMT_GOODS_PRICE_MIN":46980.0,"PREV_AMT_GOODS_PRICE_MAX":1129500.0,"PREV_AMT_GOODS_PRICE_MEAN":251066.4545454546,"PREV_HOUR_APPR_PROCESS_START_MIN":8.0,"PREV_HOUR_APPR_PROCESS_START_MAX":17.0,"PREV_HOUR_APPR_PROCESS_START_MEAN":13.0714285714,"PREV_RATE_DOWN_PAYMENT_MIN":0.0987367326,"PREV_RATE_DOWN_PAYMENT_MAX":0.2042709335,"PREV_RATE_DOWN_PAYMENT_MEAN":0.1244417797,"PREV_DAYS_DECISION_MIN":-2358.0,"PREV_DAYS_DECISION_MAX":-25.0,"PREV_DAYS_DECISION_MEAN":-875.5714285714,"PREV_CNT_PAYMENT_MEAN":16.9090909091,"PREV_CNT_PAYMENT_SUM":186.0,"APPROVED_AMT_ANNUITY_MIN":4774.005,"APPROVED_AMT_ANNUITY_MAX":27891.54,"APPROVED_AMT_ANNUITY_MEAN":14319.151875,"APPROVED_AMT_APPLICATION_MIN":46980.0,"APPROVED_AMT_APPLICATION_MAX":315000.0,"APPROVED_AMT_APPLICATION_MEAN":149466.375,"APPROVED_AMT_CREDIT_MIN":42970.5,"APPROVED_AMT_CREDIT_MAX":386577.0,"APPROVED_AMT_CREDIT_MEAN":172356.1875,"APPROVED_APP_CREDIT_PERC_MIN":0.7594185702,"APPROVED_APP_CREDIT_PERC_MAX":1.1836734694,"APPROVED_APP_CREDIT_PERC_MEAN":0.9777368176,"APPROVED_APP_CREDIT_PERC_VAR":0.025763731,"APPROVED_AMT_DOWN_PAYMENT_MIN":4698.0,"APPROVED_AMT_DOWN_PAYMENT_MAX":15876.0,"APPROVED_AMT_DOWN_PAYMENT_MEAN":8361.0,"APPROVED_AMT_GOODS_PRICE_MIN":46980.0,"APPROVED_AMT_GOODS_PRICE_MAX":315000.0,"APPROVED_AMT_GOODS_PRICE_MEAN":149466.375,"APPROVED_HOUR_APPR_PROCESS_START_MIN":8.0,"APPROVED_HOUR_APPR_PROCESS_START_MAX":17.0,"APPROVED_HOUR_APPR_PROCESS_START_MEAN":13.0,"APPROVED_RATE_DOWN_PAYMENT_MIN":0.0987367326,"APPROVED_RATE_DOWN_PAYMENT_MAX":0.2042709335,"APPROVED_RATE_DOWN_PAYMENT_MEAN":0.1244417797,"APPROVED_DAYS_DECISION_MIN":-2358.0,"APPROVED_DAYS_DECISION_MAX":-305.0,"APPROVED_DAYS_DECISION_MEAN":-1324.0,"APPROVED_CNT_PAYMENT_MEAN":14.25,"APPROVED_CNT_PAYMENT_SUM":114.0,"REFUSED_AMT_ANNUITY_MIN":14419.62,"REFUSED_AMT_ANNUITY_MAX":34253.1,"REFUSED_AMT_ANNUITY_MEAN":21474.24,"REFUSED_AMT_APPLICATION_MIN":121500.0,"REFUSED_AMT_APPLICATION_MAX":1129500.0,"REFUSED_AMT_APPLICATION_MEAN":522000.0,"REFUSED_AMT_CREDIT_MIN":121500.0,"REFUSED_AMT_CREDIT_MAX":1293502.5,"REFUSED_AMT_CREDIT_MEAN":576667.5,"REFUSED_APP_CREDIT_PERC_MIN":0.8732105272,"REFUSED_APP_CREDIT_PERC_MAX":1.0,"REFUSED_APP_CREDIT_PERC_MEAN":0.9577368424,"REFUSED_APP_CREDIT_PERC_VAR":0.0053585235,"REFUSED_AMT_DOWN_PAYMENT_MIN":null,"REFUSED_AMT_DOWN_PAYMENT_MAX":null,"REFUSED_AMT_DOWN_PAYMENT_MEAN":null,"REFUSED_AMT_GOODS_PRICE_MIN":121500.0,"REFUSED_AMT_GOODS_PRICE_MAX":1129500.0,"REFUSED_AMT_GOODS_PRICE_MEAN":522000.0,"REFUSED_HOUR_APPR_PROCESS_START_MIN":13.0,"REFUSED_HOUR_APPR_PROCESS_START_MAX":14.0,"REFUSED_HOUR_APPR_PROCESS_START_MEAN":13.3333333333,"REFUSED_RATE_DOWN_PAYMENT_MIN":null,"REFUSED_RATE_DOWN_PAYMENT_MAX":null,"REFUSED_RATE_DOWN_PAYMENT_MEAN":null,"REFUSED_DAYS_DECISION_MIN":-503.0,"REFUSED_DAYS_DECISION_MAX":-25.0,"REFUSED_DAYS_DECISION_MEAN":-277.6666666667,"REFUSED_CNT_PAYMENT_MEAN":24.0,"REFUSED_CNT_PAYMENT_SUM":72.0,"POS_MONTHS_BALANCE_MAX":-1.0,"POS_MONTHS_BALANCE_MEAN":-44.724137931,"POS_MONTHS_BALANCE_SIZE":58.0,"POS_SK_DPD_MAX":11.0,"POS_SK_DPD_MEAN":0.1896551724,"POS_SK_DPD_DEF_MAX":0.0,"POS_SK_DPD_DEF_MEAN":0.0,"POS_COUNT":58.0,"INSTAL_NUM_INSTALMENT_VERSION_NUNIQUE":2.0,"INSTAL_DPD_MAX":11.0,"INSTAL_DPD_MEAN":0.22,"INSTAL_DPD_SUM":11.0,"INSTAL_DBD_MAX":29.0,"INSTAL_DBD_MEAN":12.66,"INSTAL_DBD_SUM":633.0,"INSTAL_PAYMENT_PERC_MAX":1.0,"INSTAL_PAYMENT_PERC_MEAN":0.98,"INSTAL_PAYMENT_PERC_SUM":49.0,"INSTAL_PAYMENT_PERC_VAR":0.0192362919,"INSTAL_PAYMENT_DIFF_MAX":15544.125,"INSTAL_PAYMENT_DIFF_MEAN":316.9278,"INSTAL_PAYMENT_DIFF_SUM":15846.39,"INSTAL_PAYMENT_DIFF_VAR":4830388.2576573063,"INSTAL_AMT_INSTALMENT_MAX":287563.365,"INSTAL_AMT_INSTALMENT_MEAN":17768.0556,"INSTAL_AMT_INSTALMENT_SUM":888402.78,"INSTAL_AMT_PAYMENT_MIN":302.265,"INSTAL_AMT_PAYMENT_MAX":287563.365,"INSTAL_AMT_PAYMENT_MEAN":17451.1278,"INSTAL_AMT_PAYMENT_SUM":872556.39,"INSTAL_DAYS_ENTRY_PAYMENT_MAX":-8.0,"INSTAL_DAYS_ENTRY_PAYMENT_MEAN":-1355.12,"INSTAL_DAYS_ENTRY_PAYMENT_SUM":-67756.0,"INSTAL_COUNT":50.0,"CC_MONTHS_BALANCE_MIN":null,"CC_MONTHS_BALANCE_MAX":null,"CC_MONTHS_BALANCE_MEAN":null,"CC_MONTHS_BALANCE_SUM":null,"CC_MONTHS_BALANCE_VAR":null,"CC_AMT_BALANCE_MIN":null,"CC_AMT_BALANCE_MAX":null,"CC_AMT_BALANCE_MEAN":null,"CC_AMT_BALANCE_SUM":null,"CC_AMT_BALANCE_VAR":null,"CC_AMT_CREDIT_LIMIT_ACTUAL_MIN":null,"CC_AMT_CREDIT_LIMIT_ACTUAL_MAX":null,"CC_AMT_CREDIT_LIMIT_ACTUAL_MEAN":null,"CC_AMT_CREDIT_LIMIT_ACTUAL_SUM":null,"CC_AMT_CREDIT_LIMIT_ACTUAL_VAR":null,"CC_AMT_DRAWINGS_ATM_CURRENT_MIN":null,"CC_AMT_DRAWINGS_ATM_CURRENT_MAX":null,"CC_AMT_DRAWINGS_ATM_CURRENT_MEAN":null,"CC_AMT_DRAWINGS_ATM_CURRENT_SUM":null,"CC_AMT_DRAWINGS_ATM_CURRENT_VAR":null,"CC_AMT_DRAWINGS_CURRENT_MIN":null,"CC_AMT_DRAWINGS_CURRENT_MAX":null,"CC_AMT_DRAWINGS_CURRENT_MEAN":null,"CC_AMT_DRAWINGS_CURRENT_SUM":null,"CC_AMT_DRAWINGS_CURRENT_VAR":null,"CC_AMT_DRAWINGS_OTHER_CURRENT_MIN":null,"CC_AMT_DRAWINGS_OTHER_CURRENT_MAX":null,"CC_AMT_DRAWINGS_OTHER_CURRENT_MEAN":null,"CC_AMT_DRAWINGS_OTHER_CURRENT_SUM":null,"CC_AMT_DRAWINGS_OTHER_CURRENT_VAR":null,"CC_AMT_DRAWINGS_POS_CURRENT_MIN":null,"CC_AMT_DRAWINGS_POS_CURRENT_MAX":null,"CC_AMT_DRAWINGS_POS_CURRENT_MEAN":null,"CC_AMT_DRAWINGS_POS_CURRENT_SUM":null,"CC_AMT_DRAWINGS_POS_CURRENT_VAR":null,"CC_AMT_INST_MIN_REGULARITY_MIN":null,"CC_AMT_INST_MIN_REGULARITY_MAX":null,"CC_AMT_INST_MIN_REGULARITY_MEAN":null,"CC_AMT_INST_MIN_REGULARITY_SUM":null,"CC_AMT_INST_MIN_REGULARITY_VAR":null,"CC_AMT_PAYMENT_CURRENT_MIN":null,"CC_AMT_PAYMENT_CURRENT_MAX":null,"CC_AMT_PAYMENT_CURRENT_MEAN":null,"CC_AMT_PAYMENT_CURRENT_SUM":null,"CC_AMT_PAYMENT_CURRENT_VAR":null,"CC_AMT_PAYMENT_TOTAL_CURRENT_MIN":null,"CC_AMT_PAYMENT_TOTAL_CURRENT_MAX":null,"CC_AMT_PAYMENT_TOTAL_CURRENT_MEAN":null,"CC_AMT_PAYMENT_TOTAL_CURRENT_SUM":null,"CC_AMT_PAYMENT_TOTAL_CURRENT_VAR":null,"CC_AMT_RECEIVABLE_PRINCIPAL_MIN":null,"CC_AMT_RECEIVABLE_PRINCIPAL_MAX":null,"CC_AMT_RECEIVABLE_PRINCIPAL_MEAN":null,"CC_AMT_RECEIVABLE_PRINCIPAL_SUM":null,"CC_AMT_RECEIVABLE_PRINCIPAL_VAR":null,"CC_AMT_RECIVABLE_MIN":null,"CC_AMT_RECIVABLE_MAX":null,"CC_AMT_RECIVABLE_MEAN":null,"CC_AMT_RECIVABLE_SUM":null,"CC_AMT_RECIVABLE_VAR":null,"CC_AMT_TOTAL_RECEIVABLE_MIN":null,"CC_AMT_TOTAL_RECEIVABLE_MAX":null,"CC_AMT_TOTAL_RECEIVABLE_MEAN":null,"CC_AMT_TOTAL_RECEIVABLE_SUM":null,"CC_AMT_TOTAL_RECEIVABLE_VAR":null,"CC_CNT_DRAWINGS_ATM_CURRENT_MIN":null,"CC_CNT_DRAWINGS_ATM_CURRENT_MAX":null,"CC_CNT_DRAWINGS_ATM_CURRENT_MEAN":null,"CC_CNT_DRAWINGS_ATM_CURRENT_SUM":null,"CC_CNT_DRAWINGS_ATM_CURRENT_VAR":null,"CC_CNT_DRAWINGS_CURRENT_MIN":null,"CC_CNT_DRAWINGS_CURRENT_MAX":null,"CC_CNT_DRAWINGS_CURRENT_MEAN":null,"CC_CNT_DRAWINGS_CURRENT_SUM":null,"CC_CNT_DRAWINGS_CURRENT_VAR":null,"CC_CNT_DRAWINGS_OTHER_CURRENT_MIN":null,"CC_CNT_DRAWINGS_OTHER_CURRENT_MAX":null,"CC_CNT_DRAWINGS_OTHER_CURRENT_MEAN":null,"CC_CNT_DRAWINGS_OTHER_CURRENT_SUM":null,"CC_CNT_DRAWINGS_OTHER_CURRENT_VAR":null,"CC_CNT_DRAWINGS_POS_CURRENT_MIN":null,"CC_CNT_DRAWINGS_POS_CURRENT_MAX":null,"CC_CNT_DRAWINGS_POS_CURRENT_MEAN":null,"CC_CNT_DRAWINGS_POS_CURRENT_SUM":null,"CC_CNT_DRAWINGS_POS_CURRENT_VAR":null,"CC_CNT_INSTALMENT_MATURE_CUM_MIN":null,"CC_CNT_INSTALMENT_MATURE_CUM_MAX":null,"CC_CNT_INSTALMENT_MATURE_CUM_MEAN":null,"CC_CNT_INSTALMENT_MATURE_CUM_SUM":null,"CC_CNT_INSTALMENT_MATURE_CUM_VAR":null,"CC_SK_DPD_MIN":null,"CC_SK_DPD_MAX":null,"CC_SK_DPD_MEAN":null,"CC_SK_DPD_SUM":null,"CC_SK_DPD_VAR":null,"CC_SK_DPD_DEF_MIN":null,"CC_SK_DPD_DEF_MAX":null,"CC_SK_DPD_DEF_MEAN":null,"CC_SK_DPD_DEF_SUM":null,"CC_SK_DPD_DEF_VAR":null,"CC_COUNT":null}